bot/__init__.py
bot/admin.py
bot/apps.py
bot/filters.py
bot/models.py
bot/router.py
bot/states.py
bot/types.py
bot/urls.py
bot/utils.py
bot/views.py
bot/migrations/0001_initial.py
bot/migrations/__init__.py
config/__init__.py
config/asgi.py
config/settings.py
config/urls.py
config/wsgi.py
django_open_bot-0.1.2.dist-info/METADATA
django_open_bot-0.1.2.dist-info/WHEEL
django_open_bot-0.1.2.dist-info/top_level.txt
django_open_bot-0.1.2.dist-info/RECORD
