Metadata-Version: 2.4
Name: django_open_bot
Version: 0.1.2
Home-page: https://github.com/username/mycoolapp
Author: Shohzodbek
Author-email: vipfthef@gmail.com
Classifier: Framework :: Django
Classifier: Programming Language :: Python :: 3
Requires-Dist: django
Requires-Dist: requests
Requires-Dist: aiohttp
Dynamic: author
Dynamic: author-email
Dynamic: classifier
Dynamic: home-page
Dynamic: requires-dist
